gita/__init__.py
gita/constant.py
gita/data.py
gita/utils.py
gita_py-0.1.2.dist-info/licenses/LICENSE
gita_py-0.1.2.dist-info/METADATA
gita_py-0.1.2.dist-info/WHEEL
gita_py-0.1.2.dist-info/top_level.txt
gita_py-0.1.2.dist-info/RECORD
